force_deps/__init__.py
force_deps-0.1.0.dist-info/LICENSE.md
force_deps-0.1.0.dist-info/METADATA
force_deps-0.1.0.dist-info/WHEEL
force_deps-0.1.0.dist-info/top_level.txt
force_deps-0.1.0.dist-info/RECORD
