Metadata-Version: 2.1
Name: force-deps
Version: 0.1.0
Summary: a small package for enforcing package requirements at the class- or function-level
Home-page: https://github.com/maxblee/force_deps
Author: Max Lee
Author-email: maxbmhlee@gmail.com
License: BSD
Download-URL: https://github.com/maxblee/force_deps/tarball/0.1.0
Platform: UNKNOWN
Classifier: Development Status :: 3 - Alpha
Classifier: Intended Audience :: Developers
Classifier: Programming Language :: Python :: 3
